{
  "fileName": "EFTA01281093.pdf",
  "dataSet": "10",
  "documentType": "financial record",
  "dateOriginal": "2014-10-30",
  "summary": "This document appears to be a financial transaction record involving MWR Licensing LLC and SCiO Verum Corp. It details a payment of $945.02 made on October 30, 2014, indicating a business relationship between the two entities.",
  "persons": [],
  "connections": [],
  "events": [],
  "locations": [
    "70310 Chartv.Til Center Drive, Cornelius, NC 28031",
    "27 High Tech Blvd, Thomasville, NC 27360, US"
  ],
  "keyFacts": [
    "A payment of $945.02 was made from MWR Licensing LLC to SCiO Verum Corp.",
    "The transaction occurred on October 30, 2014.",
    "The document contains references to multiple confidential identifiers."
  ],
  "analyzedAt": "2026-02-21T12:26:21.874Z"
}