{
  "fileName": "EFTA00140544.pdf",
  "dataSet": "9",
  "documentType": "other",
  "dateOriginal": null,
  "summary": "This document appears to be a schedule or organizational chart for a correctional facility, possibly related to the Metropolitan Correctional Center (MCC) where Jeffrey Epstein was held. It lists various departments, programs, and staff roles within the facility, along with a calendar grid.",
  "persons": [],
  "connections": [],
  "events": [],
  "locations": [],
  "keyFacts": [
    "Document appears to be an internal schedule or organizational chart for a correctional facility.",
    "Lists various departments and roles including Wardell, AW Programs, AW Operations, Exec. Assistant, Captain, Correctional System, Computer Services, Duty Officer, DHO, Education/Roc, Facilities, Financial Management, Food Services, Physician Assistant, Psychology, Religious Services, Safety, SIA/SIS, Unit Teams.",
    "Includes a calendar grid with days Sunday through Saturday and date references (e.g., 18122.1212130).",
    "Contains a promotional reference to 'BetterManagers.com' with the tagline 'We make good managers better'.",
    "Document is part of the Epstein case files with identifier EFTA00140544 and references a related file EFTA00140545."
  ],
  "analyzedAt": "2026-02-19T23:37:39.311Z"
}