{
  "fileName": "EFTA01281784.pdf",
  "dataSet": "10",
  "documentType": "other",
  "dateOriginal": null,
  "summary": "The document appears to be a confidential order related to payments, possibly involving financial transactions or records. Specific details are redacted, and the context is unclear due to the minimal text provided.",
  "persons": [],
  "connections": [],
  "events": [],
  "locations": [],
  "keyFacts": [
    "The document is marked as confidential.",
    "It references financial transactions with amounts indicated.",
    "Specific names and details are redacted or not present."
  ],
  "analyzedAt": "2026-02-21T12:57:08.172Z"
}