{
  "fileName": "EFTA00159154.pdf",
  "dataSet": "9",
  "documentType": "pre-trial preparation notes",
  "dateOriginal": "2021-11-24",
  "summary": "This document appears to be notes prepared for trial testimony, likely from a witness or victim, containing previously undisclosed or clarifying recollections. It mentions not remembering if asked about other girls and describes being touched by GM.",
  "persons": [],
  "connections": [
    {
      "person1": "GM",
      "person2": "JE",
      "relationshipType": "associate",
      "description": "Both are mentioned in the same testimony notes regarding events involving the witness.",
      "strength": 2
    }
  ],
  "events": [
    {
      "date": null,
      "title": "Massage incident with GM",
      "description": "The witness states that GM touched her breasts during a massage.",
      "category": "abuse",
      "significance": 4,
      "personsInvolved": [
        "GM"
      ]
    },
    {
      "date": "2021-11-24",
      "title": "Pre-trial testimony preparation",
      "description": "Notes were prepared for trial testimony, containing clarifying or different recollections.",
      "category": "legal",
      "significance": 3,
      "personsInvolved": []
    }
  ],
  "locations": [
    "NM"
  ],
  "keyFacts": [
    "The document is prepared for trial testimony and contains previously undisclosed or clarifying recollections.",
    "A witness states that GM touched her breasts during a massage.",
    "The witness does not remember if she was asked about other girls not being in NM by JE or GM.",
    "The document is subject to a protective order covering specific paragraphs."
  ],
  "analyzedAt": "2026-02-21T03:06:06.077Z"
}