{
  "fileName": "EFTA00155470.pdf",
  "dataSet": "9",
  "documentType": "correspondence",
  "dateOriginal": "2021-05-13",
  "summary": "This appears to be a brief, informal email or text message exchange discussing the health of an unnamed individual and acknowledging the importance of contributing to a case. The sender notes the trial date has been set and promises future updates.",
  "persons": [],
  "connections": [],
  "events": [
    {
      "date": "2021-05-13",
      "title": "Communication about health and case",
      "description": "An exchange of messages where the sender clarifies their previous comments were not meant to be dismissive, emphasizes their focus on helping an unnamed individual's health journey, and acknowledges the importance of the case. The sender also provides a heads-up about a trial date being set.",
      "category": "legal",
      "significance": 2,
      "personsInvolved": []
    }
  ],
  "locations": [],
  "keyFacts": [
    "The document is a personal communication from May 13, 2021, referencing a 'health journey' of an unnamed individual.",
    "The sender expresses understanding of the importance of contributing to an unspecified case.",
    "The communication mentions that a trial date has been set, indicating ongoing legal proceedings.",
    "Key individuals (sender, recipient, and the person on the health journey) are not named in the provided text."
  ],
  "analyzedAt": "2026-02-20T13:36:07.708Z"
}