{
  "fileName": "EFTA01297956.pdf",
  "dataSet": "10",
  "documentType": "other",
  "dateOriginal": null,
  "summary": "This document appears to be a search result from the Offshore Leaks Database by the International Consortium of Investigative Journalists, specifically focusing on the name 'Richard Kahn'. The search yielded no results related to offshore entities, officers, intermediaries, or addresses associated with this name.",
  "persons": [],
  "connections": [],
  "events": [],
  "locations": [],
  "keyFacts": [
    "The search for 'Richard Kahn' in the Offshore Leaks Database returned no results.",
    "The document is part of a confidential search result related to offshore financial investigations.",
    "The document is dated 8/22/2018."
  ],
  "analyzedAt": "2026-02-21T21:32:18.155Z"
}