{
  "fileName": "EFTA01281836.pdf",
  "dataSet": "10",
  "documentType": "financial record",
  "dateOriginal": null,
  "summary": "This document appears to be a financial record related to a mobile deposit made at Fifth Third Bank. It includes details such as the deposit amount and date but lacks significant context or named individuals.",
  "persons": [],
  "connections": [],
  "events": [],
  "locations": [],
  "keyFacts": [
    "The document records a mobile deposit made on August 20, 2014.",
    "The deposit amount was $593.37.",
    "The deposit was made at Fifth Third Bank.",
    "The document is marked as confidential.",
    "No named individuals are mentioned in the document."
  ],
  "analyzedAt": "2026-02-21T12:59:04.047Z"
}