{
  "fileName": "EFTA01342565.pdf",
  "dataSet": "10",
  "documentType": "other",
  "dateOriginal": "2020-07-01",
  "summary": "This document contains location data for a mobile number associated with the Epstein case, indicating its geographical coordinates and confidence level of the location estimate. It emphasizes the caution needed when using this data for investigative purposes due to potential inaccuracies.",
  "persons": [],
  "connections": [],
  "events": [],
  "locations": [
    {
      "longitude": -71.89819,
      "latitude": 43.22512,
      "radiusMeters": 9545
    }
  ],
  "keyFacts": [
    "The mobile number was located on 2020-07-01 at 11:02:12 GMT.",
    "The location data is sourced from AT&T's 4G-GMPC system.",
    "The confidence level of the location estimate is 90%.",
    "The document warns about the potential inaccuracies in the location data.",
    "No specific individuals are mentioned in the document."
  ],
  "analyzedAt": "2026-02-22T14:21:37.054Z"
}