{
  "fileName": "EFTA01285957.pdf",
  "dataSet": "10",
  "documentType": "financial record",
  "dateOriginal": "2016-01-01",
  "summary": "This document is a financial statement from Deutsche Bank detailing account activity for the period from January 1, 2016, to January 31, 2016. It includes information on account balances, deposits, withdrawals, service charges, and interest earned. The statement outlines the procedures for reporting errors and inquiries related to the account.",
  "persons": [],
  "connections": [],
  "events": [],
  "locations": [
    "345 Park Avenue, New York, NY 10154",
    "575 Lexington Ave, New York, NY 10022"
  ],
  "keyFacts": [
    "The account balance at the beginning of January 2016 was $6,256.36.",
    "A total of $50.00 was paid in service charges during the statement period.",
    "Interest earned during the statement period was $1.06.",
    "The document outlines procedures for reporting errors related to electronic and non-electronic funds transfers.",
    "The statement includes contact information for inquiries regarding the account."
  ],
  "analyzedAt": "2026-02-21T15:33:56.019Z"
}