{
  "fileName": "EFTA00124640.pdf",
  "dataSet": "9",
  "documentType": "financial record",
  "dateOriginal": "2019-01-14",
  "summary": "This is a bank withdrawal record from Municipal Credit Union's Coney Island Branch showing a $100.00 cash withdrawal from a FastTrack Checking account on January 14, 2019. The document appears to be a standard ATM/bank transaction receipt.",
  "persons": [],
  "connections": [],
  "events": [
    {
      "date": "2019-01-14",
      "title": "Cash Withdrawal from FastTrack Checking",
      "description": "$100.00 cash withdrawal from a FastTrack Checking account at Municipal Credit Union's Coney Island Branch via card swipe.",
      "category": "financial",
      "significance": 1,
      "personsInvolved": []
    }
  ],
  "locations": [
    "Municipal Credit Union Coney Island Branch, 1904 Surf Avenue, Brooklyn, NY 11224"
  ],
  "keyFacts": [
    "A $100.00 cash withdrawal occurred on January 14, 2019 at 3:24pm from a FastTrack Checking account.",
    "The transaction took place at Municipal Credit Union's Coney Island Branch in Brooklyn, NY.",
    "The withdrawal was made via card swipe, leaving a new balance of $1,905.64.",
    "The document is a financial record with reference number EFTA00124640.",
    "No named individuals are identified in this transaction record."
  ],
  "analyzedAt": "2026-02-19T13:32:43.671Z"
}