{
  "fileName": "EFTA00005832.pdf",
  "dataSet": "4",
  "documentType": "other",
  "dateOriginal": "2019-06-06",
  "summary": "This appears to be a screenshot or record from the New York eJusticeNY Integrated Justice Portal, showing a DMV photo request transaction for an individual with a case number, dated June 6, 2019. The document contains minimal substantive text about the Epstein case.",
  "persons": [],
  "connections": [],
  "events": [
    {
      "date": "2019-06-06",
      "title": "DMV Photo Request Transaction",
      "description": "A DMV photo request was processed through the New York eJusticeNY Integrated Justice Portal for an individual associated with a case number.",
      "category": "investigation",
      "significance": 1,
      "personsInvolved": []
    }
  ],
  "locations": [],
  "keyFacts": [
    "Document shows a DMV photo request transaction from the New York eJusticeNY Integrated Justice Portal.",
    "Transaction date is June 6, 2019, which is after Jeffrey Epstein's July 2019 arrest.",
    "Case number 31ENY3027175 and individual ID 1168491 are referenced but no names are visible.",
    "The document appears to be a system screenshot or record, not a narrative document.",
    "Minimal case-specific information is present in the provided text."
  ],
  "analyzedAt": "2026-02-08T03:24:10.212Z"
}