{
  "fileName": "EFTA00039797.pdf",
  "dataSet": "9",
  "documentType": "correspondence",
  "dateOriginal": "2021-04-19",
  "summary": "This document is an email chain between Assistant United States Attorneys in the Southern District of New York regarding a draft letter to be filed with the court on April 19, 2021. It shows coordination among prosecutors on a legal filing related to the Epstein case.",
  "persons": [],
  "connections": [],
  "events": [
    {
      "date": "2021-04-19",
      "title": "Prosecutors prepare court filing",
      "description": "Assistant United States Attorneys in the Southern District of New York draft and edit a letter for filing with the court regarding the Epstein case.",
      "category": "legal",
      "significance": 2,
      "personsInvolved": []
    }
  ],
  "locations": [
    {
      "name": "One Saint Andrew's Plaza",
      "city": "New York",
      "state": "NY",
      "country": "USA",
      "context": "Office address of the Assistant United States Attorney in the Southern District of New York"
    },
    {
      "name": "Southern District of New York",
      "city": "New York",
      "state": "NY",
      "country": "USA",
      "context": "Federal judicial district handling the Epstein case"
    }
  ],
  "keyFacts": [
    "Prosecutors in the Southern District of New York were actively working on the Epstein case as of April 2021.",
    "The document shows coordination among Assistant United States Attorneys on a legal filing.",
    "The email chain includes edits to a draft letter intended for court filing.",
    "All personal names in the document appear to be redacted or represented by placeholders."
  ],
  "analyzedAt": "2026-02-11T14:26:33.875Z"
}