{
  "fileName": "EFTA00159155.pdf",
  "dataSet": "9",
  "documentType": "other",
  "dateOriginal": null,
  "summary": "This appears to be a heavily redacted or corrupted document page, possibly a legal filing or transcript, with minimal legible text. The visible text includes a file number, a page count, and a note that it is subject to a protective order covering specific paragraphs.",
  "persons": [],
  "connections": [],
  "events": [],
  "locations": [],
  "keyFacts": [
    "The document is heavily corrupted or redacted, with very little legible text for analysis.",
    "The document is subject to a protective order covering paragraphs 7, 8, 9, 10, 15, and 17.",
    "The document is identified as page 1 of 1 with file references EFTA_00008472 and EFTA00159155."
  ],
  "analyzedAt": "2026-02-21T03:06:11.231Z"
}