{
  "fileName": "EFTA00111800.pdf",
  "dataSet": "9",
  "documentType": "voluntary interview waiver form",
  "dateOriginal": null,
  "summary": "This is a standard Office of the Inspector General voluntary interview waiver form, used to document that an employee is voluntarily providing information as part of an investigation. The form includes warnings about the voluntary nature of the interview and potential use of statements in future proceedings.",
  "persons": [],
  "connections": [],
  "events": [],
  "locations": [],
  "keyFacts": [
    "The document is a voluntary interview waiver form from the U.S. Department of Justice Office of the Inspector General.",
    "The form is used to inform an employee that an OIG investigation is being conducted and that their participation is voluntary.",
    "The form warns that statements provided may be used as evidence in future criminal or disciplinary proceedings.",
    "The employee must sign a waiver acknowledging they understand the warnings and are participating voluntarily.",
    "The form includes signature lines for an OIG Special Agent, a witness, and the employee."
  ],
  "analyzedAt": "2026-02-19T09:21:14.778Z"
}