{
  "fileName": "EFTA01281788.pdf",
  "dataSet": "10",
  "documentType": "other",
  "dateOriginal": null,
  "summary": "The document appears to be a financial order or transaction record related to a payment, but the text is largely garbled and lacks coherent information. It contains references to a private bank and includes some confidential markings, suggesting it may pertain to financial dealings in the Epstein case.",
  "persons": [],
  "connections": [],
  "events": [],
  "locations": [],
  "keyFacts": [
    "The document references a payment order involving a private bank.",
    "The text is heavily garbled and lacks clear context or identifiable individuals.",
    "There are multiple redacted or unclear references, making it difficult to extract specific details."
  ],
  "analyzedAt": "2026-02-21T12:57:16.238Z"
}