{
  "fileName": "EFTA00007959.pdf",
  "dataSet": "4",
  "documentType": "police evidence inventory",
  "dateOriginal": null,
  "summary": "This appears to be a police evidence inventory sheet from the Town of Palm Beach Police Department, listing items in the Epstein case. The document references multiple evidence item numbers (EFTA00007959, EFTA00007960, EFTA00007961) but the content is largely garbled or incomplete, with one item noted as 'not scanned'.",
  "persons": [],
  "connections": [],
  "events": [],
  "locations": [
    "Town of Palm Beach"
  ],
  "keyFacts": [
    "Document is a police evidence inventory from the Town of Palm Beach Police Department.",
    "References evidence items EFTA00007959, EFTA00007960, and EFTA00007961.",
    "One item (EFTA00007960) is noted as 'not scanned', indicating missing or unavailable evidence."
  ],
  "analyzedAt": "2026-02-07T23:24:15.047Z"
}