{
  "fileName": "EFTA00160096.pdf",
  "dataSet": "9",
  "documentType": "correspondence",
  "dateOriginal": "2020-12-10",
  "summary": "This document is a calendar entry for an accepted call scheduled for December 10, 2020, between 18:00 and 19:00 UTC, involving the 'Maxwell Team'. It appears to be a personal-class event related to the legal defense or associates of Ghislaine Maxwell.",
  "persons": [],
  "connections": [],
  "events": [
    {
      "date": "2020-12-10",
      "title": "Maxwell Team Call",
      "description": "A scheduled one-hour call involving the 'Maxwell Team', classified as a personal event.",
      "category": "legal",
      "significance": 2,
      "personsInvolved": []
    }
  ],
  "locations": [],
  "keyFacts": [
    "A call involving the 'Maxwell Team' was scheduled for December 10, 2020.",
    "The event was classified as 'X-PERSONAL' and given a high priority (5).",
    "The document is a calendar entry, indicating planning or coordination among Maxwell's associates or legal team."
  ],
  "analyzedAt": "2026-02-21T04:11:14.785Z"
}