{
  "fileName": "EFTA00019593.pdf",
  "dataSet": "8",
  "documentType": "correspondence",
  "dateOriginal": "2021-03-28",
  "summary": "An email from an unidentified sender to a team regarding an upcoming grand jury presentation on March 29, 2021. The email attaches a script outline and PowerPoint presentation for review and invites team members to join the presentation.",
  "persons": [],
  "connections": [],
  "events": [
    {
      "date": "2021-03-29",
      "title": "Grand Jury Presentation",
      "description": "A scheduled grand jury presentation for which a script and PowerPoint were prepared.",
      "category": "legal",
      "significance": 3,
      "personsInvolved": []
    }
  ],
  "locations": [],
  "keyFacts": [
    "A grand jury presentation was scheduled for March 29, 2021.",
    "The email sender prepared a script outline and PowerPoint presentation for the grand jury.",
    "The email invites team members to provide feedback on the materials and to attend the presentation."
  ],
  "analyzedAt": "2026-02-08T01:16:34.988Z"
}