{
  "fileName": "EFTA01281856.pdf",
  "dataSet": "10",
  "documentType": "financial record",
  "dateOriginal": null,
  "summary": "This document appears to be a financial record related to deposits at Fifth Third Bank, indicating that certain deposits may not be available for immediate withdrawal. The document includes various financial figures and counts but lacks specific details about individuals or events.",
  "persons": [],
  "connections": [],
  "events": [],
  "locations": [],
  "keyFacts": [
    "The document mentions deposits that may not be available for immediate withdrawal.",
    "It references Fifth Third Bank as the financial institution involved.",
    "The document includes various currency counts but does not specify any individuals."
  ],
  "analyzedAt": "2026-02-21T12:59:59.455Z"
}