{
  "fileName": "EFTA01332994.pdf",
  "dataSet": "10",
  "documentType": "call detail/toll records",
  "dateOriginal": "2005-07-25",
  "summary": "This document contains call detail records from BellSouth for various target numbers associated with the Epstein case. It includes timestamps, call durations, and other metadata related to the calls made to and from these numbers. The records are subject to a protective order, indicating sensitive information is contained within.",
  "persons": [],
  "connections": [],
  "events": [],
  "locations": [],
  "keyFacts": [
    "The document contains call detail records dated July 25, 2005.",
    "Multiple target numbers are referenced, but no named individuals are mentioned.",
    "The records include timestamps and durations of calls, indicating extensive communication activity.",
    "The document is subject to a protective order, suggesting the information is sensitive.",
    "No specific events or incidents are detailed in the document."
  ],
  "analyzedAt": "2026-02-22T12:05:17.840Z"
}