{
  "fileName": "EFTA00003115.pdf",
  "dataSet": "1",
  "documentType": "other",
  "dateOriginal": null,
  "summary": "This document appears to be a garbled or corrupted file containing technical specifications for an HP Slimline 260-a010 DT PC, along with some fragmented text and a file reference (EFTA00003115). There is no substantive content related to the Epstein case, persons, events, or locations. The text is primarily technical product information and warranty details.",
  "persons": [],
  "connections": [],
  "events": [],
  "locations": [],
  "keyFacts": [
    "The document is file EFTA00003115.pdf from Data Set 1.",
    "The content is corrupted or garbled, containing technical specifications for an HP Slimline 260-a010 DT PC.",
    "No meaningful information related to the Epstein case, individuals, or events can be extracted from this text.",
    "The document includes product numbers, serial numbers, warranty information, and regulatory compliance codes.",
    "The text appears to be a mix of technical data and possibly corrupted metadata, with no coherent narrative or case-related content."
  ],
  "analyzedAt": "2026-02-11T22:55:43.674Z"
}