{
  "fileName": "EFTA01281898.pdf",
  "dataSet": "10",
  "documentType": "financial record",
  "dateOriginal": null,
  "summary": "This document appears to be a financial record related to a mobile deposit made into a Fifth Third Bank account. It includes details such as the deposit date, time, and amount, but lacks any named individuals or significant contextual information.",
  "persons": [],
  "connections": [],
  "events": [],
  "locations": [],
  "keyFacts": [
    "The document records a mobile deposit made on April 28, 2016.",
    "The amount of the deposit was $16.10.",
    "The document is marked as confidential."
  ],
  "analyzedAt": "2026-02-21T13:01:50.567Z"
}