{
  "fileName": "EFTA01285594.pdf",
  "dataSet": "10",
  "documentType": "financial record",
  "dateOriginal": "2015-06-30",
  "summary": "This document is a summary of account balances and transactions for a Deutsche Bank account held by Gratitude Americ/4 Ltd for the period of June 1, 2015, to June 30, 2015. It details the beginning and ending balances, deposits, withdrawals, service charges, and interest earned during this period.",
  "persons": [],
  "connections": [],
  "events": [],
  "locations": [
    "345 Park Avenue, New York, NY 10154",
    "6100 Red Hook Quarter, St. Thomas, US Virgin Islands 00802"
  ],
  "keyFacts": [
    "The account balance at the beginning of June 1, 2015, was $1,000.32.",
    "The ending balance as of June 30, 2015, was $1,000.32.",
    "Interest earned during the period was $0.08.",
    "There were no overdraft fees or NSF item fees during this statement period.",
    "The document includes contact information for inquiries regarding the account."
  ],
  "analyzedAt": "2026-02-21T15:16:36.785Z"
}