{
  "fileName": "EFTA01286029.pdf",
  "dataSet": "10",
  "documentType": "financial record",
  "dateOriginal": "2016-02-01",
  "summary": "This document is a financial statement from Deutsche Bank detailing account balances and transactions for Gratitude America, Ltd. for the period from February 1, 2016, to February 29, 2016. It includes information on deposits, withdrawals, service charges, and interest payments.",
  "persons": [],
  "connections": [],
  "events": [],
  "locations": [
    "New York, NY",
    "St Thomas, United States Virgin Islands"
  ],
  "keyFacts": [
    "The account balance for Gratitude America, Ltd. as of February 29, 2016, was $9,533,533.39.",
    "A funds transfer of $150,000.00 was made on February 3, 2016.",
    "Interest payment of $1,516.34 was credited on February 29, 2016.",
    "Service charges included a total of $50.00 for NSF return item fees during the statement period.",
    "The document outlines procedures for reporting errors or inquiries regarding the account."
  ],
  "analyzedAt": "2026-02-21T15:37:56.215Z"
}