{
  "fileName": "EFTA00155471.pdf",
  "dataSet": "9",
  "documentType": "correspondence",
  "dateOriginal": null,
  "summary": "This appears to be a text message exchange discussing travel arrangements, including an itinerary for arrival on the 25th and departure on the 29th, and coordination of return flights for multiple individuals including children. The context suggests it may relate to travel planning associated with Jeffrey Epstein's network.",
  "persons": [],
  "connections": [],
  "events": [
    {
      "date": null,
      "title": "Travel coordination for arrival and departure",
      "description": "Text exchange about sending a new itinerary for arrival on the 25th and departure on the 29th, and working on return flights for everyone.",
      "category": "travel",
      "significance": 2,
      "personsInvolved": []
    }
  ],
  "locations": [],
  "keyFacts": [
    "The document is a text message exchange about travel arrangements.",
    "It mentions arrival on the 25th and departure on the 29th of an unspecified month.",
    "The sender is working on return flights for multiple people, including children.",
    "There is discussion about email delivery issues and checking junk mail.",
    "The context suggests coordination within a group traveling together."
  ],
  "analyzedAt": "2026-02-20T13:36:14.580Z"
}