{
  "fileName": "EFTA01298419.pdf",
  "dataSet": "10",
  "documentType": "other",
  "dateOriginal": null,
  "summary": "The document appears to be a search result from the Offshore Leaks Database by the International Consortium of Investigative Journalists, specifically focusing on the search term 'Harry Beller'. It indicates that no results were found for this individual in relation to offshore entities, officers, intermediaries, or addresses.",
  "persons": [],
  "connections": [],
  "events": [],
  "locations": [],
  "keyFacts": [
    "No results were found for 'Harry Beller' in the Offshore Leaks Database.",
    "The document is part of a search conducted on 8/22/2018.",
    "The Offshore Leaks Database is maintained by the International Consortium of Investigative Journalists."
  ],
  "analyzedAt": "2026-02-21T21:47:59.258Z"
}