{
  "fileName": "EFTA01344301.pdf",
  "dataSet": "10",
  "documentType": "financial record",
  "dateOriginal": null,
  "summary": "This document appears to be a financial statement for Southern Financial, LLC, detailing investments in various equity markets for the period of July 1, 2013, to July 31, 2013. It includes information on unrealized gains and losses, accrued yields, and specific equity investments, including those in non-US and emerging markets.",
  "persons": [],
  "connections": [],
  "events": [],
  "locations": [],
  "keyFacts": [
    "The document details financial transactions and performance for Southern Financial, LLC.",
    "It covers the period from July 1, 2013, to July 31, 2013.",
    "Investments include non-US equity and emerging market equity.",
    "Specific financial figures are provided, including unrealized gains and losses.",
    "No named individuals are mentioned in the document."
  ],
  "analyzedAt": "2026-02-22T16:00:18.382Z"
}