{
  "fileName": "EFTA00001930.pdf",
  "dataSet": "1",
  "documentType": "correspondence",
  "dateOriginal": null,
  "summary": "This appears to be a fragment of personal correspondence expressing gratitude and discussing financial matters, possibly related to Jeffrey Epstein's network. The text is heavily garbled with OCR errors but contains phrases suggesting personal thanks and financial transactions.",
  "persons": [],
  "connections": [],
  "events": [],
  "locations": [],
  "keyFacts": [
    "Document contains heavily garbled text with significant OCR errors making specific names and details unreadable",
    "Phrases suggest expressions of gratitude ('wonderful thing you have done', 'thank you for everything you have done')",
    "Mentions financial matters ('considerable amount', 'moved out') but specific amounts and parties are unclear",
    "Document appears to be personal correspondence rather than official legal or investigative material",
    "No clear named individuals, dates, or specific events can be reliably extracted due to poor text quality"
  ],
  "analyzedAt": "2026-02-12T01:18:37.890Z"
}